projects/voting_machine.v
module buttoncontrol(
    input clock,
    input reset,
    input button,
    output reg valid_vote
);

    reg [30:0] counter;

    // Count how long the button is pressed
    always @(posedge clock)
    begin
        if (reset)
            counter <= 0;
        else
        begin
            if (button && counter < 11)
                counter <= counter + 1;
            else if (!button)
                counter <= 0;
        end
    end

    // Generate valid vote signal
    always @(posedge clock)
    begin
        if (reset)
            valid_vote <= 1'b0;
        else
        begin
            if (counter == 10)
                valid_vote <= 1'b1;
            else
                valid_vote <= 1'b0;
        end
    end

endmodule


// ============================================================
// VOTE LOGGER
// ============================================================

module votelogger(
    input clock,
    input reset,
    input mode,

    input cand1_vote_valid,
    input cand2_vote_valid,
    input cand3_vote_valid,
    input cand4_vote_valid,

    output reg [7:0] cand1_vote_recvd,
    output reg [7:0] cand2_vote_recvd,
    output reg [7:0] cand3_vote_recvd,
    output reg [7:0] cand4_vote_recvd
);

    always @(posedge clock)
    begin
        if (reset)
        begin
            cand1_vote_recvd <= 0;
            cand2_vote_recvd <= 0;
            cand3_vote_recvd <= 0;
            cand4_vote_recvd <= 0;
        end
        else
        begin
            if (cand1_vote_valid && mode == 0)
                cand1_vote_recvd <= cand1_vote_recvd + 1;

            else if (cand2_vote_valid && mode == 0)
                cand2_vote_recvd <= cand2_vote_recvd + 1;

            else if (cand3_vote_valid && mode == 0)
                cand3_vote_recvd <= cand3_vote_recvd + 1;

            else if (cand4_vote_valid && mode == 0)
                cand4_vote_recvd <= cand4_vote_recvd + 1;
        end
    end

endmodule


// ============================================================
// MODE CONTROL
// ============================================================

module modeControl(
    input clock,
    input reset,
    input mode,
    input valid_vote_casted,

    input [7:0] candidate1_vote,
    input [7:0] candidate2_vote,
    input [7:0] candidate3_vote,
    input [7:0] candidate4_vote,

    input candidate1_button_press,
    input candidate2_button_press,
    input candidate3_button_press,
    input candidate4_button_press,

    output reg [7:0] leds
);

    reg [30:0] counter;

    // LED timer after valid vote
    always @(posedge clock)
    begin
        if (reset)
            counter <= 0;

        else if (valid_vote_casted)
            counter <= counter + 1;

        else if (counter != 0 && counter < 10)
            counter <= counter + 1;

        else
            counter <= 0;
    end


    // LED control
    always @(posedge clock)
    begin
        if (reset)
            leds <= 0;

        else
        begin

            // Voting mode
            if (mode == 0 && counter > 0)
                leds <= 8'hFF;

            else if (mode == 0)
                leds <= 8'h00;

            // Result mode
            else if (mode == 1)
            begin
                if (candidate1_button_press)
                    leds <= candidate1_vote;

                else if (candidate2_button_press)
                    leds <= candidate2_vote;

                else if (candidate3_button_press)
                    leds <= candidate3_vote;

                else if (candidate4_button_press)
                    leds <= candidate4_vote;
            end
        end
    end

endmodule


// ============================================================
// TOP MODULE
// ============================================================

module votingMachine(
    input clock,
    input reset,
    input mode,

    input button1,
    input button2,
    input button3,
    input button4,

    output [7:0] led
);

    wire valid_vote_1;
    wire valid_vote_2;
    wire valid_vote_3;
    wire valid_vote_4;

    wire [7:0] cand1_vote_recvd;
    wire [7:0] cand2_vote_recvd;
    wire [7:0] cand3_vote_recvd;
    wire [7:0] cand4_vote_recvd;

    wire anyValidVote;


    // Any candidate has a valid vote
    assign anyValidVote = valid_vote_1 |
                          valid_vote_2 |
                          valid_vote_3 |
                          valid_vote_4;


    // --------------------------------------------------------
    // Button Control - Candidate 1
    // --------------------------------------------------------

    buttoncontrol bc1(
        .clock(clock),
        .reset(reset),
        .button(button1),
        .valid_vote(valid_vote_1)
    );


    // --------------------------------------------------------
    // Button Control - Candidate 2
    // --------------------------------------------------------

    buttoncontrol bc2(
        .clock(clock),
        .reset(reset),
        .button(button2),
        .valid_vote(valid_vote_2)
    );


    // --------------------------------------------------------
    // Button Control - Candidate 3
    // --------------------------------------------------------

    buttoncontrol bc3(
        .clock(clock),
        .reset(reset),
        .button(button3),
        .valid_vote(valid_vote_3)
    );


    // --------------------------------------------------------
    // Button Control - Candidate 4
    // --------------------------------------------------------

    buttoncontrol bc4(
        .clock(clock),
        .reset(reset),
        .button(button4),
        .valid_vote(valid_vote_4)
    );


    // --------------------------------------------------------
    // Vote Logger
    // --------------------------------------------------------

    votelogger VL(
        .clock(clock),
        .reset(reset),
        .mode(mode),

        .cand1_vote_valid(valid_vote_1),
        .cand2_vote_valid(valid_vote_2),
        .cand3_vote_valid(valid_vote_3),
        .cand4_vote_valid(valid_vote_4),

        .cand1_vote_recvd(cand1_vote_recvd),
        .cand2_vote_recvd(cand2_vote_recvd),
        .cand3_vote_recvd(cand3_vote_recvd),
        .cand4_vote_recvd(cand4_vote_recvd)
    );


    // --------------------------------------------------------
    // Mode Control
    // --------------------------------------------------------

    modeControl MC(
        .clock(clock),
        .reset(reset),
        .mode(mode),

        .valid_vote_casted(anyValidVote),

        .candidate1_vote(cand1_vote_recvd),
        .candidate2_vote(cand2_vote_recvd),
        .candidate3_vote(cand3_vote_recvd),
        .candidate4_vote(cand4_vote_recvd),

        .candidate1_button_press(valid_vote_1),
        .candidate2_button_press(valid_vote_2),
        .candidate3_button_press(valid_vote_3),
        .candidate4_button_press(valid_vote_4),

        .leds(led)
    );

endmodule

// https://github.com/seenivasankamalakannan1202/projects.git

projects/test_voting.v
`timescale 1ns/1ps

module votingMachine_tb;

    reg clock;
    reg reset;
    reg mode;

    reg button1;
    reg button2;
    reg button3;
    reg button4;

  wire [7:0] led;


    // ==========================================
    // DUT - Design Under Test
    // ==========================================

    votingMachine dut (
        .clock(clock),
        .reset(reset),
        .mode(mode),

        .button1(button1),
        .button2(button2),
        .button3(button3),
        .button4(button4),

        .led(led)
    );


    // ==========================================
    // Clock Generation
    // Period = 10 ns
    // ==========================================

    always #5 clock = ~clock;


    // ==========================================
    // VCD File Generation
    // ==========================================

    initial begin

        $dumpfile("votingMachine.vcd");
        $dumpvars(0, votingMachine_tb);

    end


    // ==========================================
    // Test Cases
    // ==========================================

    initial begin

        // Initial values

        clock   = 0;
        reset   = 1;
        mode    = 0;

        button1 = 0;
        button2 = 0;
        button3 = 0;
        button4 = 0;


        // ======================================
        // RESET
        // ======================================

        #20;

        reset = 0;


        // ======================================
        // VOTING MODE
        // mode = 0
        // ======================================

        mode = 0;


        // Candidate 1 - Vote 1
        button1 = 1;
        #120;

        button1 = 0;
        #30;


        // Candidate 2 - Vote 1
        button2 = 1;
        #120;

        button2 = 0;
        #30;


        // Candidate 1 - Vote 2
        button1 = 1;
        #120;

        button1 = 0;
        #30;


        // Candidate 3 - Vote 1
        button3 = 1;
        #120;

        button3 = 0;
        #30;


        // ======================================
        // RESULT MODE
        // mode = 1
        // ======================================

        mode = 1;

        #20;


        // Candidate 1 result
        button1 = 1;
        #120;

        button1 = 0;
        #30;


        // Candidate 2 result
        button2 = 1;
        #120;

        button2 = 0;
        #30;


        // Candidate 3 result
        button3 = 1;
        #120;

        button3 = 0;
        #30;


        // Candidate 4 result
        button4 = 1;
        #120;

        button4 = 0;
        #30;


        // ======================================
        // End Simulation
        // ======================================

        #50;

        $finish;

    end


    // ==========================================
    // Display values in terminal
    // ==========================================

    initial begin

        $monitor(
            "Time=%0t | reset=%b | mode=%b | B1=%b B2=%b B3=%b B4=%b | LED=%b",
            $time,
            reset,
            mode,
            button1,
            button2,
            button3,
            button4,
            led
        );

    end

endmodule

projects/votingMachine.vcd
$date
	Sun Jul 26 22:54:15 2026
$end
$version
	Icarus Verilog
$end
$timescale
	1ps
$end
$scope module votingMachine_tb $end
$var wire 8 ! led [7:0] $end
$var reg 1 " button1 $end
$var reg 1 # button2 $end
$var reg 1 $ button3 $end
$var reg 1 % button4 $end
$var reg 1 & clock $end
$var reg 1 ' mode $end
$var reg 1 ( reset $end
$scope module dut $end
$var wire 1 ) anyValidVote $end
$var wire 1 " button1 $end
$var wire 1 # button2 $end
$var wire 1 $ button3 $end
$var wire 1 % button4 $end
$var wire 1 & clock $end
$var wire 1 ' mode $end
$var wire 1 ( reset $end
$var wire 1 * valid_vote_4 $end
$var wire 1 + valid_vote_3 $end
$var wire 1 , valid_vote_2 $end
$var wire 1 - valid_vote_1 $end
$var wire 8 . led [7:0] $end
$var wire 8 / cand4_vote_recvd [7:0] $end
$var wire 8 0 cand3_vote_recvd [7:0] $end
$var wire 8 1 cand2_vote_recvd [7:0] $end
$var wire 8 2 cand1_vote_recvd [7:0] $end
$scope module MC $end
$var wire 1 & clock $end
$var wire 1 ' mode $end
$var wire 1 ( reset $end
$var wire 1 ) valid_vote_casted $end
$var wire 8 3 candidate4_vote [7:0] $end
$var wire 1 * candidate4_button_press $end
$var wire 8 4 candidate3_vote [7:0] $end
$var wire 1 + candidate3_button_press $end
$var wire 8 5 candidate2_vote [7:0] $end
$var wire 1 , candidate2_button_press $end
$var wire 8 6 candidate1_vote [7:0] $end
$var wire 1 - candidate1_button_press $end
$var reg 31 7 counter [30:0] $end
$var reg 8 8 leds [7:0] $end
$upscope $end
$scope module VL $end
$var wire 1 & clock $end
$var wire 1 ' mode $end
$var wire 1 ( reset $end
$var wire 1 * cand4_vote_valid $end
$var wire 1 + cand3_vote_valid $end
$var wire 1 , cand2_vote_valid $end
$var wire 1 - cand1_vote_valid $end
$var reg 8 9 cand1_vote_recvd [7:0] $end
$var reg 8 : cand2_vote_recvd [7:0] $end
$var reg 8 ; cand3_vote_recvd [7:0] $end
$var reg 8 < cand4_vote_recvd [7:0] $end
$upscope $end
$scope module bc1 $end
$var wire 1 " button $end
$var wire 1 & clock $end
$var wire 1 ( reset $end
$var reg 31 = counter [30:0] $end
$var reg 1 - valid_vote $end
$upscope $end
$scope module bc2 $end
$var wire 1 # button $end
$var wire 1 & clock $end
$var wire 1 ( reset $end
$var reg 31 > counter [30:0] $end
$var reg 1 , valid_vote $end
$upscope $end
$scope module bc3 $end
$var wire 1 $ button $end
$var wire 1 & clock $end
$var wire 1 ( reset $end
$var reg 31 ? counter [30:0] $end
$var reg 1 + valid_vote $end
$upscope $end
$scope module bc4 $end
$var wire 1 % button $end
$var wire 1 & clock $end
$var wire 1 ( reset $end
$var reg 31 @ counter [30:0] $end
$var reg 1 * valid_vote $end
$upscope $end
$upscope $end
$upscope $end
$enddefinitions $end
#0
$dumpvars
bx @
bx ?
bx >
bx =
bx <
bx ;
bx :
bx 9
bx 8
bx 7
bx 6
bx 5
bx 4
bx 3
bx 2
bx 1
bx 0
bx /
bx .
x-
x,
x+
x*
x)
1(
0'
0&
0%
0$
0#
0"
bx !
$end
#5000
0)
b0 =
0-
b0 >
0,
b0 ?
0+
b0 @
0*
b0 /
b0 3
b0 <
b0 0
b0 4
b0 ;
b0 1
b0 5
b0 :
b0 2
b0 6
b0 9
b0 7
b0 !
b0 .
b0 8
1&
#10000
0&
#15000
1&
#20000
0&
1"
0(
#25000
b1 =
1&
#30000
0&
#35000
b10 =
1&
#40000
0&
#45000
b11 =
1&
#50000
0&
#55000
b100 =
1&
#60000
0&
#65000
b101 =
1&
#70000
0&
#75000
b110 =
1&
#80000
0&
#85000
b111 =
1&
#90000
0&
#95000
b1000 =
1&
#100000
0&
#105000
b1001 =
1&
#110000
0&
#115000
b1010 =
1&
#120000
0&
#125000
1)
b1011 =
1-
1&
#130000
0&
#135000
0)
b1 7
b1 2
b1 6
b1 9
0-
1&
#140000
0&
0"
#145000
b0 =
b10 7
b11111111 !
b11111111 .
b11111111 8
1&
#150000
0&
#155000
b11 7
1&
#160000
0&
#165000
b100 7
1&
#170000
0&
1#
#175000
b101 7
b1 >
1&
#180000
0&
#185000
b10 >
b110 7
1&
#190000
0&
#195000
b111 7
b11 >
1&
#200000
0&
#205000
b100 >
b1000 7
1&
#210000
0&
#215000
b1001 7
b101 >
1&
#220000
0&
#225000
b110 >
b1010 7
1&
#230000
0&
#235000
b0 7
b111 >
1&
#240000
0&
#245000
b1000 >
b0 !
b0 .
b0 8
1&
#250000
0&
#255000
b1001 >
1&
#260000
0&
#265000
b1010 >
1&
#270000
0&
#275000
1)
1,
b1011 >
1&
#280000
0&
#285000
0)
0,
b1 1
b1 5
b1 :
b1 7
1&
#290000
0&
0#
#295000
b11111111 !
b11111111 .
b11111111 8
b10 7
b0 >
1&
#300000
0&
#305000
b11 7
1&
#310000
0&
#315000
b100 7
1&
#320000
0&
1"
#325000
b1 =
b101 7
1&
#330000
0&
#335000
b110 7
b10 =
1&
#340000
0&
#345000
b11 =
b111 7
1&
#350000
0&
#355000
b1000 7
b100 =
1&
#360000
0&
#365000
b101 =
b1001 7
1&
#370000
0&
#375000
b1010 7
b110 =
1&
#380000
0&
#385000
b111 =
b0 7
1&
#390000
0&
#395000
b0 !
b0 .
b0 8
b1000 =
1&
#400000
0&
#405000
b1001 =
1&
#410000
0&
#415000
b1010 =
1&
#420000
0&
#425000
1)
b1011 =
1-
1&
#430000
0&
#435000
0)
b1 7
b10 2
b10 6
b10 9
0-
1&
#440000
0&
0"
#445000
b0 =
b10 7
b11111111 !
b11111111 .
b11111111 8
1&
#450000
0&
#455000
b11 7
1&
#460000
0&
#465000
b100 7
1&
#470000
0&
1$
#475000
b101 7
b1 ?
1&
#480000
0&
#485000
b10 ?
b110 7
1&
#490000
0&
#495000
b111 7
b11 ?
1&
#500000
0&
#505000
b100 ?
b1000 7
1&
#510000
0&
#515000
b1001 7
b101 ?
1&
#520000
0&
#525000
b110 ?
b1010 7
1&
#530000
0&
#535000
b0 7
b111 ?
1&
#540000
0&
#545000
b1000 ?
b0 !
b0 .
b0 8
1&
#550000
0&
#555000
b1001 ?
1&
#560000
0&
#565000
b1010 ?
1&
#570000
0&
#575000
1)
1+
b1011 ?
1&
#580000
0&
#585000
0)
0+
b1 0
b1 4
b1 ;
b1 7
1&
#590000
0&
0$
#595000
b11111111 !
b11111111 .
b11111111 8
b10 7
b0 ?
1&
#600000
0&
#605000
b11 7
1&
#610000
0&
#615000
b100 7
1&
#620000
0&
1'
#625000
b101 7
1&
#630000
0&
#635000
b110 7
1&
#640000
0&
1"
#645000
b1 =
b111 7
1&
#650000
0&
#655000
b1000 7
b10 =
1&
#660000
0&
#665000
b11 =
b1001 7
1&
#670000
0&
#675000
b1010 7
b100 =
1&
#680000
0&
#685000
b101 =
b0 7
1&
#690000
0&
#695000
b110 =
1&
#700000
0&
#705000
b111 =
1&
#710000
0&
#715000
b1000 =
1&
#720000
0&
#725000
b1001 =
1&
#730000
0&
#735000
b1010 =
1&
#740000
0&
#745000
1)
b1011 =
1-
1&
#750000
0&
#755000
0)
b10 !
b10 .
b10 8
b1 7
0-
1&
#760000
0&
0"
#765000
b0 =
b10 7
1&
#770000
0&
#775000
b11 7
1&
#780000
0&
#785000
b100 7
1&
#790000
0&
1#
#795000
b101 7
b1 >
1&
#800000
0&
#805000
b10 >
b110 7
1&
#810000
0&
#815000
b111 7
b11 >
1&
#820000
0&
#825000
b100 >
b1000 7
1&
#830000
0&
#835000
b1001 7
b101 >
1&
#840000
0&
#845000
b110 >
b1010 7
1&
#850000
0&
#855000
b0 7
b111 >
1&
#860000
0&
#865000
b1000 >
1&
#870000
0&
#875000
b1001 >
1&
#880000
0&
#885000
b1010 >
1&
#890000
0&
#895000
1)
1,
b1011 >
1&
#900000
0&
#905000
0)
0,
b1 7
b1 !
b1 .
b1 8
1&
#910000
0&
0#
#915000
b10 7
b0 >
1&
#920000
0&
#925000
b11 7
1&
#930000
0&
#935000
b100 7
1&
#940000
0&
1$
#945000
b1 ?
b101 7
1&
#950000
0&
#955000
b110 7
b10 ?
1&
#960000
0&
#965000
b11 ?
b111 7
1&
#970000
0&
#975000
b1000 7
b100 ?
1&
#980000
0&
#985000
b101 ?
b1001 7
1&
#990000
0&
#995000
b1010 7
b110 ?
1&
#1000000
0&
#1005000
b111 ?
b0 7
1&
#1010000
0&
#1015000
b1000 ?
1&
#1020000
0&
#1025000
b1001 ?
1&
#1030000
0&
#1035000
b1010 ?
1&
#1040000
0&
#1045000
1)
b1011 ?
1+
1&
#1050000
0&
#1055000
0)
b1 7
0+
1&
#1060000
0&
0$
#1065000
b0 ?
b10 7
1&
#1070000
0&
#1075000
b11 7
1&
#1080000
0&
#1085000
b100 7
1&
#1090000
0&
1%
#1095000
b101 7
b1 @
1&
#1100000
0&
#1105000
b10 @
b110 7
1&
#1110000
0&
#1115000
b111 7
b11 @
1&
#1120000
0&
#1125000
b100 @
b1000 7
1&
#1130000
0&
#1135000
b1001 7
b101 @
1&
#1140000
0&
#1145000
b110 @
b1010 7
1&
#1150000
0&
#1155000
b0 7
b111 @
1&
#1160000
0&
#1165000
b1000 @
1&
#1170000
0&
#1175000
b1001 @
1&
#1180000
0&
#1185000
b1010 @
1&
#1190000
0&
#1195000
1)
1*
b1011 @
1&
#1200000
0&
#1205000
0)
0*
b1 7
b0 !
b0 .
b0 8
1&
#1210000
0&
0%
#1215000
b10 7
b0 @
1&
#1220000
0&
#1225000
b11 7
1&
#1230000
0&
#1235000
b100 7
1&
#1240000
0&
#1245000
b101 7
1&
#1250000
0&
#1255000
b110 7
1&
#1260000
0&
#1265000
b111 7
1&
#1270000
0&
#1275000
b1000 7
1&
#1280000
0&
#1285000
b1001 7
1&
